README.rst
setup.py
django_matialvarezs_grafana_customers.egg-info/PKG-INFO
django_matialvarezs_grafana_customers.egg-info/SOURCES.txt
django_matialvarezs_grafana_customers.egg-info/dependency_links.txt
django_matialvarezs_grafana_customers.egg-info/requires.txt
django_matialvarezs_grafana_customers.egg-info/top_level.txt
matialvarezs_grafana_customers/__init__.py
matialvarezs_grafana_customers/admin.py
matialvarezs_grafana_customers/api.py
matialvarezs_grafana_customers/apps.py
matialvarezs_grafana_customers/base_dashboard.py
matialvarezs_grafana_customers/base_row_dashboard.py
matialvarezs_grafana_customers/base_target.py
matialvarezs_grafana_customers/context_processors.py
matialvarezs_grafana_customers/decorators.py
matialvarezs_grafana_customers/definitions.py
matialvarezs_grafana_customers/dispatcher.py
matialvarezs_grafana_customers/errors.py
matialvarezs_grafana_customers/manage_dashboard.py
matialvarezs_grafana_customers/manage_folders.py
matialvarezs_grafana_customers/manage_organisations.py
matialvarezs_grafana_customers/manage_panels.py
matialvarezs_grafana_customers/manage_rows_dashboard.py
matialvarezs_grafana_customers/manage_users.py
matialvarezs_grafana_customers/managers.py
matialvarezs_grafana_customers/middlewares.py
matialvarezs_grafana_customers/models.py
matialvarezs_grafana_customers/serializers.py
matialvarezs_grafana_customers/settings.py
matialvarezs_grafana_customers/signals.py
matialvarezs_grafana_customers/tests.py
matialvarezs_grafana_customers/urls.py
matialvarezs_grafana_customers/utils.py
matialvarezs_grafana_customers/views.py
matialvarezs_grafana_customers/influxdb/__init__.py
matialvarezs_grafana_customers/influxdb/base_panel.py
matialvarezs_grafana_customers/influxdb/base_target.py
matialvarezs_grafana_customers/influxdb/base_target_gauge.py
matialvarezs_grafana_customers/management/__init__.py
matialvarezs_grafana_customers/management/commands/__init__.py
matialvarezs_grafana_customers/management/commands/matialvarezs_grafana_customers_test_command.py
matialvarezs_grafana_customers/migrations/0001_initial.py
matialvarezs_grafana_customers/migrations/0002_auto_20180414_2121.py
matialvarezs_grafana_customers/migrations/0003_auto_20180520_2235.py
matialvarezs_grafana_customers/migrations/0004_panelsbyrowdashboardgrafana.py
